<customcontrol>
<version>
459365
</version>
<ccSingleVersionNumber>
1
</ccSingleVersionNumber>
<bank>
0
</bank>
<macro>
29
</macro>
<size>
58
</size>
<name>
P130</name>
<macros offset="0">
<size>
28
</size>
<area>
19
</area>
<me>
0
</me>
<placeholder>
0
</placeholder>
<cmd>
154
</cmd>
<data>
13384a100743414d20313a4e4557533a3133303a32</data>
</macros>
<macros offset="30">
<size>
26
</size>
<area>
19
</area>
<me>
0
</me>
<placeholder>
0
</placeholder>
<cmd>
246
</cmd>
<data>
4e110743414d20313a4e4557533a3133303a32</data>
</macros>
</customcontrol>
