<shotbox>
<name>
AM MAIN</name>
<ref>
<bttn id="0">
1536
</bttn>
<bttn id="1">
1537
</bttn>
<bttn id="2">
1538
</bttn>
<bttn id="3">
1539
</bttn>
<bttn id="4">
1540
</bttn>
<bttn id="5">
1541
</bttn>
<bttn id="6">
1542
</bttn>
<bttn id="7">
2328
</bttn>
<bttn id="8">
2329
</bttn>
<bttn id="9">
2330
</bttn>
<bttn id="10">
2320
</bttn>
<bttn id="11">
11822
</bttn>
<bttn id="12">
11822
</bttn>
<bttn id="13">
11822
</bttn>
<bttn id="14">
2816
</bttn>
<bttn id="15">
2818
</bttn>
<bttn id="16">
2820
</bttn>
<bttn id="17">
2822
</bttn>
<bttn id="18">
2830
</bttn>
<bttn id="19">
2832
</bttn>
<bttn id="20">
2834
</bttn>
<bttn id="21">
2817
</bttn>
<bttn id="22">
2819
</bttn>
<bttn id="23">
2821
</bttn>
<bttn id="24">
2823
</bttn>
<bttn id="25">
2831
</bttn>
<bttn id="26">
2833
</bttn>
<bttn id="27">
2835
</bttn>
</ref>
<version>
459365
</version>
<mnem_style>
<colour>
4
</colour>
<reserved>
8
</reserved>
<brightOffset>
192
</brightOffset>
</mnem_style>
</shotbox>
